{"add":{"path":"part-00000-a15aafe6-262b-44ce-953a-97bc95e82494-c000.snappy.parquet","partitionValues":{},"size":310,"modificationTime":1731860751647,"dataChange":true,"stats":"{\"numRecords\":0,\"minValues\":{},\"maxValues\":{},\"nullCount\":{}}"}}
{"add":{"path":"part-00001-03cd197c-248a-483d-bbb3-72659e838ef0-c000.snappy.parquet","partitionValues":{},"size":498,"modificationTime":1731860751742,"dataChange":true,"stats":"{\"numRecords\":1,\"minValues\":{\"value\":\"message1\"},\"maxValues\":{\"value\":\"message1\"},\"nullCount\":{\"value\":0}}"}}
{"remove":{"path":"part-00000-5bd9e853-974f-4115-a4c7-58fc4c3c8e3c-c000.snappy.parquet","deletionTimestamp":1731860751983,"dataChange":true,"extendedFileMetadata":true,"partitionValues":{},"size":310}}
{"remove":{"path":"part-00001-e99e1252-4e03-4215-9fe7-134d883d1464-c000.snappy.parquet","deletionTimestamp":1731860751983,"dataChange":true,"extendedFileMetadata":true,"partitionValues":{},"size":498}}
{"commitInfo":{"timestamp":1731860751991,"operation":"WRITE","operationParameters":{"mode":"Overwrite","partitionBy":"[]"},"readVersion":4,"isolationLevel":"Serializable","isBlindAppend":false,"operationMetrics":{"numFiles":"2","numOutputRows":"1","numOutputBytes":"808"},"engineInfo":"Apache-Spark/3.3.0 Delta-Lake/2.1.0","txnId":"9af8ca5f-16e4-4b96-b8ae-ea480e31701d"}}
